rplcopilot/__init__.py
rplcopilot/rpl.py
rplcopilot/src/__init__.py
rplcopilot/src/processor/Chunker.py
rplcopilot/src/processor/DocumentLoader.py
rplcopilot/src/processor/Embedder.py
rplcopilot/src/processor/Export.py
rplcopilot/src/processor/Formatters.py
rplcopilot/src/processor/QueryEngine.py
rplcopilot/src/processor/Semantic.py
rplcopilot/src/processor/VectorStore.py
rplcopilot/src/processor/__init__.py
rplcopilot/src/processor/intent_detector.py
rplcopilot/src/processor/orchestrator.py
rplcopilot/src/processor/project_vector.py
rplcopilot/src/processor/handlers/__init__.py
rplcopilot/src/processor/handlers/base.py
rplcopilot/src/processor/handlers/create_project.py
rplcopilot/src/processor/handlers/log_experiment.py
rplcopilot/src/processor/handlers/upload_file.py
rplcopilot-0.1.9.dist-info/METADATA
rplcopilot-0.1.9.dist-info/WHEEL
rplcopilot-0.1.9.dist-info/entry_points.txt
rplcopilot-0.1.9.dist-info/top_level.txt
rplcopilot-0.1.9.dist-info/RECORD
