Metadata-Version: 2.4
Name: rplcopilot
Version: 0.1.9
Summary: AI-powered lab assistant CLI
Home-page: https://github.com/Jorgecardenas1/rplcopilot
Author: Jorge Hernan Cardenas
License: MIT
Requires-Dist: typer
Requires-Dist: openai
Requires-Dist: python-dotenv
Requires-Dist: requests
Requires-Dist: langchain
Requires-Dist: langchain-openai
Requires-Dist: faiss-cpu
Requires-Dist: rich
Requires-Dist: langchain-community
Requires-Dist: pypdf
Requires-Dist: rank_bm25
Requires-Dist: unstructured
Requires-Dist: pdf2image
Requires-Dist: pdfminer
Requires-Dist: Pillow
Requires-Dist: pymupdf
